Metadata-Version: 2.1
Name: mwrpc
Version: 0.1.7
Summary: Yet Another RPC Framework.
Home-page: https://github.com/MwrPub/mwrpc-py
Author: MWR Organization
Author-email: mwr@mwr.pub
License: MIT
Platform: any
Classifier: Operating System :: OS Independent
Classifier: Intended Audience :: Developers
Classifier: License :: OSI Approved :: MIT License
Classifier: Topic :: Internet :: WWW/HTTP :: HTTP Servers
Classifier: Topic :: Software Development :: Libraries :: Application Frameworks
Classifier: Programming Language :: Python :: 3
Classifier: Programming Language :: Python :: 3.4
Classifier: Programming Language :: Python :: 3.5
Classifier: Programming Language :: Python :: 3.6
Classifier: Programming Language :: Python :: 3.7
